CHANGELOG.md
CITING.md
CODE_OF_CONDUCT.md
CONTRIBUTING.md
DEVELOPMENT.md
DISCLAIMER.md
LICENSE
MANIFEST.in
README.md
pyproject.toml
setup.py
docs/CNS.md
docs/INSTALL.md
docs/USAGE.md
docs/citing.rst
docs/conf.py
docs/contributing.rst
docs/examples.md
docs/index.rst
docs/intro.md
docs/figs/HADDOCK2-stages.png
docs/figs/HADDOCK3-logo.png
docs/figs/HADDOCK3-workflow-scheme.png
docs/modules/index.rst
docs/reference/index.rst
docs/testing/index.rst
docs/testing/integration_tests.md
docs/tutorials/continuing_runs.md
docs/tutorials/index.rst
docs/tutorials/mpi.md
docs/tutorials/user_config.rst
src/haddock/__init__.py
src/haddock/clis/__init__.py
src/haddock/clis/cli.py
src/haddock/clis/cli_analyse.py
src/haddock/clis/cli_cfg.py
src/haddock/clis/cli_clean.py
src/haddock/clis/cli_cp.py
src/haddock/clis/cli_dmn.py
src/haddock/clis/cli_mpi.py
src/haddock/clis/cli_pp.py
src/haddock/clis/cli_re.py
src/haddock/clis/cli_restraints.py
src/haddock/clis/cli_score.py
src/haddock/clis/cli_traceback.py
src/haddock/clis/cli_unpack.py
src/haddock/clis/wrapper_haddock_restraints.py
src/haddock/clis/re/__init__.py
src/haddock/clis/re/clustfcc.py
src/haddock/clis/re/clustrmsd.py
src/haddock/clis/re/score.py
src/haddock/clis/restraints/__init__.py
src/haddock/clis/restraints/active_passive_to_ambig.py
src/haddock/clis/restraints/calc_accessibility.py
src/haddock/clis/restraints/naccess.config
src/haddock/clis/restraints/passive_from_active.py
src/haddock/clis/restraints/random_removal.py
src/haddock/clis/restraints/restrain_bodies.py
src/haddock/clis/restraints/restrain_ligand.py
src/haddock/clis/restraints/validate_tbl.py
src/haddock/clis/restraints/webservice.py
src/haddock/clis/restraints/z_surface_restraints.py
src/haddock/cns/toppar/boxtyp20.pdb
src/haddock/cns/toppar/carbohydrate.param
src/haddock/cns/toppar/carbohydrate.top
src/haddock/cns/toppar/cofactors.param
src/haddock/cns/toppar/cofactors.pep
src/haddock/cns/toppar/cofactors.top
src/haddock/cns/toppar/dmso.pdb
src/haddock3.egg-info/PKG-INFO
src/haddock3.egg-info/SOURCES.txt
src/haddock3.egg-info/dependency_links.txt
src/haddock3.egg-info/entry_points.txt
src/haddock3.egg-info/requires.txt
src/haddock3.egg-info/top_level.txt
