Metadata-Version: 2.4
Name: haddock3
Version: 2025.9.1
Summary: HADDOCK3
Author-email: BonvinLab <bonvinlab.support@uu.nl>
License: Apache License 2.0
Project-URL: Homepage, https://github.com/haddocking/haddock3
Project-URL: Documentation, https://github.com/haddocking/haddock3#readme
Project-URL: Issue Tracker, https://github.com/haddocking/haddock3/issues
Project-URL: Discussion Forum, https://github.com/haddocking/haddock3/issues
Keywords: Structural Biology,Biochemistry,Docking,Protein docking,Proteins
Classifier: Development Status :: 5 - Production/Stable
Classifier: License :: OSI Approved :: Apache Software License
Classifier: Natural Language :: English
Classifier: Operating System :: POSIX
Classifier: Operating System :: POSIX :: Linux
Classifier: Operating System :: MacOS
Classifier: Intended Audience :: Science/Research
Classifier: Topic :: Scientific/Engineering :: Bio-Informatics
Classifier: Topic :: Scientific/Engineering :: Chemistry
Classifier: Topic :: Scientific/Engineering :: Physics
Classifier: Programming Language :: Python :: 3.9
Classifier: Programming Language :: Python :: 3.10
Classifier: Programming Language :: Python :: 3.11
Classifier: Programming Language :: Python :: 3.12
Classifier: Programming Language :: Python :: 3.13
Classifier: Programming Language :: Python :: 3.14
Requires-Python: <3.15,>=3.9
License-File: LICENSE
Requires-Dist: pdb-tools>=2.5.0
Requires-Dist: biopython==1.*
Requires-Dist: jsonpickle>=2.1.0
Requires-Dist: numpy==2.*
Requires-Dist: pyyaml>=6.0
Requires-Dist: scipy>=1.10.0
Requires-Dist: toml>=0.10.2
Requires-Dist: pandas==2.*
Requires-Dist: prodigy-prot==2.3.0
Requires-Dist: prodigy-lig==1.1.4
Requires-Dist: plotly==6.3.0
Requires-Dist: freesasa>=2.2.1
Provides-Extra: dev
Requires-Dist: coverage==7.10.6; extra == "dev"
Requires-Dist: pytest==8.4.2; extra == "dev"
Requires-Dist: pytest-cov==6.2.1; extra == "dev"
Requires-Dist: hypothesis==6.140.2; extra == "dev"
Requires-Dist: pytest-mock==3.15.1; extra == "dev"
Requires-Dist: fastapi==0.116.1; extra == "dev"
Requires-Dist: httpx==0.28.1; extra == "dev"
Requires-Dist: kaleido==1.1.0; extra == "dev"
Requires-Dist: pytest-random-order==1.2.0; extra == "dev"
Provides-Extra: docs
Requires-Dist: sphinx>=7; extra == "docs"
Requires-Dist: sphinx-argparse>=0.4.0; extra == "docs"
Requires-Dist: sphinx_rtd_theme>=3.0.1; extra == "docs"
Requires-Dist: CommonMark>=0.9.1; extra == "docs"
Requires-Dist: mock>=5.1.0; extra == "docs"
Requires-Dist: myst-parser>=3.0.1; extra == "docs"
Provides-Extra: mpi
Requires-Dist: mpi4py>=4.0.2; extra == "mpi"
Provides-Extra: notebooks
Requires-Dist: py3Dmol>=2.5.2; extra == "notebooks"
Dynamic: license-file
